[
	{
		"title": "Art Alchemy",
		"description": "An e-commerce platform for artists.",
		"image": "images/art-alchemy.jpg",
		"link": "https://kamiri-charles.github.io/art-alchemy/",
		"icons": "typescript react java spring-boot mongodb"
	},
	{
		"title": "Hifadhi",
		"description": "Secure cloud storage",
		"image": "images/hifadhi.jpg",
		"link": "https://hifadhi-0zou.onrender.com/",
		"icons": "react vite-js typescript supabase shadcn-ui tailwind-css neon-tech drizzle-orm"
	},
	{
		"title": "Chatterbox",
		"description": "A random chat app.",
		"image": "images/chatterbox.jpg",
		"link": "https://kamiri-charles.github.io/chatterbox/",
		"icons": "react typescript"
	},

	{
		"title": "Movie Quote Generator",
		"description": "A web app that generates random movie quotes",
		"image": "images/movie-quote-generator.jpg",
		"link": "https://kamiri-charles.github.io/movie-quote-generator/",
		"icons": "react javascript html5 sass"
	},

	{
		"title": "Hangman",
		"description": "The hangman game.",
		"image": "images/hangman.jpg",
		"link": "https://kamiri-charles.github.io/hangman/",
		"icons": "javascript html5 css3"
	},

	{
		"title": "King Hammer",
		"description": "Step into the royal shoes of King Hammer, a brave and mighty king on a quest to reclaim his castle from the pesky pirate pigs! Adventure awaits in this thrilling 2D platformer!",
		"image": "images/king-hammer.jpg",
		"link": "https://kamiri-charles.github.io/king-hammer/",
		"icons": "typescript html5 css3 unity"
	},

	{
		"title": "Veditas",
		"description": "A web video editor",
		"image": "images/veditas.jpg",
		"link": "https://kamiri-charles.github.io/veditas/",
		"icons": "react javascript sass video"
	},

	{
		"title": "Heal Together",
		"description": "A web teletherapy app. Still in development.",
		"image": "images/heal-together.jpg",
		"link": "https://kamiri-charles.github.io/heal-together/",
		"icons": "react javascript html5 sass"
	},

	{
		"title": "Matrix Rain Effect",
		"description": "Inspired by the matrix.",
		"image": "images/matrix-rain-effect.jpg",
		"link": "https://kamiri-charles.github.io/matrix-rain-effect/",
		"icons": "react javascript"
	},

	{
		"title": "Martial Hero",
		"description": "A 2d HTML canvas game. Still in development.",
		"image": "images/martial-hero.jpg",
		"link": "https://kamiri-charles.github.io/martial-hero/",
		"icons": "typescript html5 css3 unity"
	}
]